ndpath.py
ndpath-0.0.1.dist-info/LICENSE
ndpath-0.0.1.dist-info/METADATA
ndpath-0.0.1.dist-info/WHEEL
ndpath-0.0.1.dist-info/entry_points.txt
ndpath-0.0.1.dist-info/top_level.txt
ndpath-0.0.1.dist-info/RECORD
