Metadata-Version: 2.1
Name: ndpath
Version: 0.0.1
Summary: A command-line tool for managing and editing the PATH environment variables
Author-email: Mohamed Elashri <ndpath@elashri.com>
License: MIT
Project-URL: Homepage, https://github.com/MohamedElashri/ndpath
Project-URL: Bug Tracker, https://github.com/MohamedElashri/ndpath/issues
Keywords: paths,pathos,enviroment
Classifier: Development Status :: 4 - Beta
Classifier: Environment :: Console
Classifier: Intended Audience :: Developers
Classifier: License :: OSI Approved :: MIT License
Classifier: Programming Language :: Python :: 3
Classifier: Programming Language :: Python :: 3.7
Classifier: Programming Language :: Python :: 3.8
Classifier: Programming Language :: Python :: 3.9
Classifier: Programming Language :: Python :: 3.10
Classifier: Topic :: Utilities
License-File: LICENSE
Requires-Dist: rich
Requires-Dist: readchar
